imdb_tv_scraper/__init__.py
imdb_tv_scraper/cli.py
imdb_tv_scraper/tv_scraper.py
imdb_tv_scraper-0.1.0.dist-info/LICENSE
imdb_tv_scraper-0.1.0.dist-info/METADATA
imdb_tv_scraper-0.1.0.dist-info/WHEEL
imdb_tv_scraper-0.1.0.dist-info/entry_points.txt
imdb_tv_scraper-0.1.0.dist-info/top_level.txt
imdb_tv_scraper-0.1.0.dist-info/RECORD
